{
  "run": {
    "run_id": "20260615_001237_scheduled_3c68f2",
    "trigger_type": "scheduled",
    "status": "success",
    "started_at": "2026-06-15T00:12:37.518274",
    "finished_at": "2026-06-15T00:14:15.463082",
    "us_data_date": "2026-06-12T00:00:00",
    "target_tw_date": "2026-06-15T00:00:00",
    "message": "完成 12 檔推薦、25 筆觸發訊號"
  },
  "predictions": [
    {
      "run_id": "20260615_001237_scheduled_3c68f2",
      "target_tw_date": "2026-06-15T00:00:00",
      "tw_ticker": "2881.TW",
      "tw_name": "富邦金",
      "expected_direction": "看漲",
      "confidence_score": 77.48864401237921,
      "bullish_score": 77.48864401237921,
      "bearish_score": 0.0,
      "signal_count": 3,
      "bullish_signal_count": 3,
      "bearish_signal_count": 0,
      "best_win_rate": 0.712,
      "average_historical_return": 0.01054383430803281,
      "best_validation_win_rate": 0.6410256410256411,
      "main_us_sources": "XLF、SMH",
      "main_reason": "XLF 單日漲跌幅偏高；SMH 單日漲跌幅偏高",
      "min_lag_day": 1,
      "max_lag_day": 3,
      "created_at": "2026-06-15T00:13:56.649830",
      "beginner_decision": "看漲",
      "is_actionable": true,
      "market_risk_level": "正常",
      "risk_warning": "",
      "risk_adjusted_score": 77.48864401237921,
      "actual_return": null,
      "actual_direction": null,
      "is_correct": null,
      "open_price": null,
      "close_price": null,
      "previous_close_price": 122.0,
      "validated_at": "2026-06-15T00:14:09.103807",
      "entry_price": null,
      "entry_price_date": null,
      "impact_entry_price": 122.0,
      "impact_entry_price_date": "2026-06-12T00:00:00",
      "impact_actual_return": null,
      "impact_actual_direction": null,
      "impact_is_correct": null,
      "impact_validation_status": "觀察中",
      "t1_date": null,
      "t1_open_price": null,
      "t1_close_price": null,
      "t1_return": null,
      "t1_relative_market_return": null,
      "t1_status": "缺少目標日開盤價",
      "t2_date": null,
      "t2_open_price": null,
      "t2_close_price": null,
      "t2_return": null,
      "t2_relative_market_return": null,
      "t2_status": "缺少目標日開盤價",
      "t3_date": null,
      "t3_open_price": null,
      "t3_close_price": null,
      "t3_return": null,
      "t3_relative_market_return": null,
      "t3_status": "缺少目標日開盤價",
      "impact_t1_date": null,
      "impact_t1_open_price": null,
      "impact_t1_close_price": null,
      "impact_t1_return": null,
      "impact_t1_relative_market_return": null,
      "impact_t1_status": "尚未收盤",
      "impact_t2_date": null,
      "impact_t2_open_price": null,
      "impact_t2_close_price": null,
      "impact_t2_return": null,
      "impact_t2_relative_market_return": null,
      "impact_t2_status": "尚未收盤",
      "impact_t3_date": null,
      "impact_t3_open_price": null,
      "impact_t3_close_price": null,
      "impact_t3_return": null,
      "impact_t3_relative_market_return": null,
      "impact_t3_status": "尚未收盤",
      "best_3d_return": null,
      "worst_3d_return": null,
      "relative_best_3d_return": null,
      "trade_best_3d_return": null,
      "trade_worst_3d_return": null,
      "trade_relative_best_3d_return": null,
      "trade_validation_status": "待回填",
      "trade_is_correct": null,
      "validation_status": "觀察中",
      "validation_window_status": "未滿3個交易日"
    },
    {
      "run_id": "20260615_001237_scheduled_3c68f2",
      "target_tw_date": "2026-06-15T00:00:00",
      "tw_ticker": "2330.TW",
      "tw_name": "台積電",
      "expected_direction": "看漲",
      "confidence_score": 56.92529654291783,
      "bullish_score": 56.92529654291783,
      "bearish_score": 0.0,
      "signal_count": 2,
      "bullish_signal_count": 2,
      "bearish_signal_count": 0,
      "best_win_rate": 0.812,
      "average_historical_return": 0.01490420560647845,
      "best_validation_win_rate": 0.6632653061224489,
      "main_us_sources": "SMH",
      "main_reason": "SMH 單日漲跌幅偏高",
      "min_lag_day": 1,
      "max_lag_day": 1,
      "created_at": "2026-06-15T00:13:56.649830",
      "beginner_decision": "看漲",
      "is_actionable": true,
      "market_risk_level": "正常",
      "risk_warning": "",
      "risk_adjusted_score": 56.92529654291783,
      "actual_return": null,
      "actual_direction": null,
      "is_correct": null,
      "open_price": null,
      "close_price": null,
      "previous_close_price": 2310.0,
      "validated_at": "2026-06-15T00:14:03.163327",
      "entry_price": null,
      "entry_price_date": null,
      "impact_entry_price": 2310.0,
      "impact_entry_price_date": "2026-06-12T00:00:00",
      "impact_actual_return": null,
      "impact_actual_direction": null,
      "impact_is_correct": null,
      "impact_validation_status": "觀察中",
      "t1_date": null,
      "t1_open_price": null,
      "t1_close_price": null,
      "t1_return": null,
      "t1_relative_market_return": null,
      "t1_status": "缺少目標日開盤價",
      "t2_date": null,
      "t2_open_price": null,
      "t2_close_price": null,
      "t2_return": null,
      "t2_relative_market_return": null,
      "t2_status": "缺少目標日開盤價",
      "t3_date": null,
      "t3_open_price": null,
      "t3_close_price": null,
      "t3_return": null,
      "t3_relative_market_return": null,
      "t3_status": "缺少目標日開盤價",
      "impact_t1_date": null,
      "impact_t1_open_price": null,
      "impact_t1_close_price": null,
      "impact_t1_return": null,
      "impact_t1_relative_market_return": null,
      "impact_t1_status": "尚未收盤",
      "impact_t2_date": null,
      "impact_t2_open_price": null,
      "impact_t2_close_price": null,
      "impact_t2_return": null,
      "impact_t2_relative_market_return": null,
      "impact_t2_status": "尚未收盤",
      "impact_t3_date": null,
      "impact_t3_open_price": null,
      "impact_t3_close_price": null,
      "impact_t3_return": null,
      "impact_t3_relative_market_return": null,
      "impact_t3_status": "尚未收盤",
      "best_3d_return": null,
      "worst_3d_return": null,
      "relative_best_3d_return": null,
      "trade_best_3d_return": null,
      "trade_worst_3d_return": null,
      "trade_relative_best_3d_return": null,
      "trade_validation_status": "待回填",
      "trade_is_correct": null,
      "validation_status": "觀察中",
      "validation_window_status": "未滿3個交易日"
    },
    {
      "run_id": "20260615_001237_scheduled_3c68f2",
      "target_tw_date": "2026-06-15T00:00:00",
      "tw_ticker": "2454.TW",
      "tw_name": "聯發科",
      "expected_direction": "看漲",
      "confidence_score": 54.9234114967349,
      "bullish_score": 54.9234114967349,
      "bearish_score": 0.0,
      "signal_count": 2,
      "bullish_signal_count": 2,
      "bearish_signal_count": 0,
      "best_win_rate": 0.736,
      "average_historical_return": 0.016640558825290176,
      "best_validation_win_rate": 0.6122448979591837,
      "main_us_sources": "SMH",
      "main_reason": "SMH 單日漲跌幅偏高",
      "min_lag_day": 2,
      "max_lag_day": 3,
      "created_at": "2026-06-15T00:13:56.649830",
      "beginner_decision": "看漲",
      "is_actionable": true,
      "market_risk_level": "正常",
      "risk_warning": "",
      "risk_adjusted_score": 54.9234114967349,
      "actual_return": null,
      "actual_direction": null,
      "is_correct": null,
      "open_price": null,
      "close_price": null,
      "previous_close_price": 4180.0,
      "validated_at": "2026-06-15T00:14:08.384920",
      "entry_price": null,
      "entry_price_date": null,
      "impact_entry_price": 4180.0,
      "impact_entry_price_date": "2026-06-12T00:00:00",
      "impact_actual_return": null,
      "impact_actual_direction": null,
      "impact_is_correct": null,
      "impact_validation_status": "觀察中",
      "t1_date": null,
      "t1_open_price": null,
      "t1_close_price": null,
      "t1_return": null,
      "t1_relative_market_return": null,
      "t1_status": "缺少目標日開盤價",
      "t2_date": null,
      "t2_open_price": null,
      "t2_close_price": null,
      "t2_return": null,
      "t2_relative_market_return": null,
      "t2_status": "缺少目標日開盤價",
      "t3_date": null,
      "t3_open_price": null,
      "t3_close_price": null,
      "t3_return": null,
      "t3_relative_market_return": null,
      "t3_status": "缺少目標日開盤價",
      "impact_t1_date": null,
      "impact_t1_open_price": null,
      "impact_t1_close_price": null,
      "impact_t1_return": null,
      "impact_t1_relative_market_return": null,
      "impact_t1_status": "尚未收盤",
      "impact_t2_date": null,
      "impact_t2_open_price": null,
      "impact_t2_close_price": null,
      "impact_t2_return": null,
      "impact_t2_relative_market_return": null,
      "impact_t2_status": "尚未收盤",
      "impact_t3_date": null,
      "impact_t3_open_price": null,
      "impact_t3_close_price": null,
      "impact_t3_return": null,
      "impact_t3_relative_market_return": null,
      "impact_t3_status": "尚未收盤",
      "best_3d_return": null,
      "worst_3d_return": null,
      "relative_best_3d_return": null,
      "trade_best_3d_return": null,
      "trade_worst_3d_return": null,
      "trade_relative_best_3d_return": null,
      "trade_validation_status": "待回填",
      "trade_is_correct": null,
      "validation_status": "觀察中",
      "validation_window_status": "未滿3個交易日"
    },
    {
      "run_id": "20260615_001237_scheduled_3c68f2",
      "target_tw_date": "2026-06-15T00:00:00",
      "tw_ticker": "3711.TW",
      "tw_name": "日月光投控",
      "expected_direction": "看漲",
      "confidence_score": 52.49213179071572,
      "bullish_score": 52.49213179071572,
      "bearish_score": 0.0,
      "signal_count": 3,
      "bullish_signal_count": 3,
      "bearish_signal_count": 0,
      "best_win_rate": 0.756,
      "average_historical_return": 0.014858808832134694,
      "best_validation_win_rate": 0.6938775510204082,
      "main_us_sources": "SMH",
      "main_reason": "SMH 單日漲跌幅偏高",
      "min_lag_day": 1,
      "max_lag_day": 3,
      "created_at": "2026-06-15T00:13:56.649830",
      "beginner_decision": "看漲",
      "is_actionable": true,
      "market_risk_level": "正常",
      "risk_warning": "",
      "risk_adjusted_score": 52.49213179071572,
      "actual_return": null,
      "actual_direction": null,
      "is_correct": null,
      "open_price": null,
      "close_price": null,
      "previous_close_price": 590.0,
      "validated_at": "2026-06-15T00:14:14.577668",
      "entry_price": null,
      "entry_price_date": null,
      "impact_entry_price": 590.0,
      "impact_entry_price_date": "2026-06-12T00:00:00",
      "impact_actual_return": null,
      "impact_actual_direction": null,
      "impact_is_correct": null,
      "impact_validation_status": "觀察中",
      "t1_date": null,
      "t1_open_price": null,
      "t1_close_price": null,
      "t1_return": null,
      "t1_relative_market_return": null,
      "t1_status": "缺少目標日開盤價",
      "t2_date": null,
      "t2_open_price": null,
      "t2_close_price": null,
      "t2_return": null,
      "t2_relative_market_return": null,
      "t2_status": "缺少目標日開盤價",
      "t3_date": null,
      "t3_open_price": null,
      "t3_close_price": null,
      "t3_return": null,
      "t3_relative_market_return": null,
      "t3_status": "缺少目標日開盤價",
      "impact_t1_date": null,
      "impact_t1_open_price": null,
      "impact_t1_close_price": null,
      "impact_t1_return": null,
      "impact_t1_relative_market_return": null,
      "impact_t1_status": "尚未收盤",
      "impact_t2_date": null,
      "impact_t2_open_price": null,
      "impact_t2_close_price": null,
      "impact_t2_return": null,
      "impact_t2_relative_market_return": null,
      "impact_t2_status": "尚未收盤",
      "impact_t3_date": null,
      "impact_t3_open_price": null,
      "impact_t3_close_price": null,
      "impact_t3_return": null,
      "impact_t3_relative_market_return": null,
      "impact_t3_status": "尚未收盤",
      "best_3d_return": null,
      "worst_3d_return": null,
      "relative_best_3d_return": null,
      "trade_best_3d_return": null,
      "trade_worst_3d_return": null,
      "trade_relative_best_3d_return": null,
      "trade_validation_status": "待回填",
      "trade_is_correct": null,
      "validation_status": "觀察中",
      "validation_window_status": "未滿3個交易日"
    },
    {
      "run_id": "20260615_001237_scheduled_3c68f2",
      "target_tw_date": "2026-06-15T00:00:00",
      "tw_ticker": "3034.TW",
      "tw_name": "聯詠",
      "expected_direction": "看漲",
      "confidence_score": 43.19788766612803,
      "bullish_score": 43.19788766612803,
      "bearish_score": 0.0,
      "signal_count": 3,
      "bullish_signal_count": 3,
      "bearish_signal_count": 0,
      "best_win_rate": 0.672,
      "average_historical_return": 0.015096047623568667,
      "best_validation_win_rate": 0.5826086956521739,
      "main_us_sources": "SMH",
      "main_reason": "SMH 近 3 日漲跌幅偏高",
      "min_lag_day": 3,
      "max_lag_day": 3,
      "created_at": "2026-06-15T00:13:56.649830",
      "beginner_decision": "看漲",
      "is_actionable": true,
      "market_risk_level": "正常",
      "risk_warning": "",
      "risk_adjusted_score": 43.19788766612803,
      "actual_return": null,
      "actual_direction": null,
      "is_correct": null,
      "open_price": null,
      "close_price": null,
      "previous_close_price": 488.5,
      "validated_at": "2026-06-15T00:14:12.713729",
      "entry_price": null,
      "entry_price_date": null,
      "impact_entry_price": 488.5,
      "impact_entry_price_date": "2026-06-12T00:00:00",
      "impact_actual_return": null,
      "impact_actual_direction": null,
      "impact_is_correct": null,
      "impact_validation_status": "觀察中",
      "t1_date": null,
      "t1_open_price": null,
      "t1_close_price": null,
      "t1_return": null,
      "t1_relative_market_return": null,
      "t1_status": "缺少目標日開盤價",
      "t2_date": null,
      "t2_open_price": null,
      "t2_close_price": null,
      "t2_return": null,
      "t2_relative_market_return": null,
      "t2_status": "缺少目標日開盤價",
      "t3_date": null,
      "t3_open_price": null,
      "t3_close_price": null,
      "t3_return": null,
      "t3_relative_market_return": null,
      "t3_status": "缺少目標日開盤價",
      "impact_t1_date": null,
      "impact_t1_open_price": null,
      "impact_t1_close_price": null,
      "impact_t1_return": null,
      "impact_t1_relative_market_return": null,
      "impact_t1_status": "尚未收盤",
      "impact_t2_date": null,
      "impact_t2_open_price": null,
      "impact_t2_close_price": null,
      "impact_t2_return": null,
      "impact_t2_relative_market_return": null,
      "impact_t2_status": "尚未收盤",
      "impact_t3_date": null,
      "impact_t3_open_price": null,
      "impact_t3_close_price": null,
      "impact_t3_return": null,
      "impact_t3_relative_market_return": null,
      "impact_t3_status": "尚未收盤",
      "best_3d_return": null,
      "worst_3d_return": null,
      "relative_best_3d_return": null,
      "trade_best_3d_return": null,
      "trade_worst_3d_return": null,
      "trade_relative_best_3d_return": null,
      "trade_validation_status": "待回填",
      "trade_is_correct": null,
      "validation_status": "觀察中",
      "validation_window_status": "未滿3個交易日"
    },
    {
      "run_id": "20260615_001237_scheduled_3c68f2",
      "target_tw_date": "2026-06-15T00:00:00",
      "tw_ticker": "2303.TW",
      "tw_name": "聯電",
      "expected_direction": "看漲",
      "confidence_score": 42.389086346393384,
      "bullish_score": 42.389086346393384,
      "bearish_score": 0.0,
      "signal_count": 1,
      "bullish_signal_count": 1,
      "bearish_signal_count": 0,
      "best_win_rate": 0.668,
      "average_historical_return": 0.012918896345627168,
      "best_validation_win_rate": 0.5833333333333334,
      "main_us_sources": "SOXX",
      "main_reason": "SOXX 單日漲跌幅偏高",
      "min_lag_day": 2,
      "max_lag_day": 2,
      "created_at": "2026-06-15T00:13:56.649830",
      "beginner_decision": "看漲",
      "is_actionable": true,
      "market_risk_level": "正常",
      "risk_warning": "",
      "risk_adjusted_score": 42.389086346393384,
      "actual_return": null,
      "actual_direction": null,
      "is_correct": null,
      "open_price": null,
      "close_price": null,
      "previous_close_price": 133.5,
      "validated_at": "2026-06-15T00:13:59.729637",
      "entry_price": null,
      "entry_price_date": null,
      "impact_entry_price": 133.5,
      "impact_entry_price_date": "2026-06-12T00:00:00",
      "impact_actual_return": null,
      "impact_actual_direction": null,
      "impact_is_correct": null,
      "impact_validation_status": "觀察中",
      "t1_date": null,
      "t1_open_price": null,
      "t1_close_price": null,
      "t1_return": null,
      "t1_relative_market_return": null,
      "t1_status": "缺少目標日開盤價",
      "t2_date": null,
      "t2_open_price": null,
      "t2_close_price": null,
      "t2_return": null,
      "t2_relative_market_return": null,
      "t2_status": "缺少目標日開盤價",
      "t3_date": null,
      "t3_open_price": null,
      "t3_close_price": null,
      "t3_return": null,
      "t3_relative_market_return": null,
      "t3_status": "缺少目標日開盤價",
      "impact_t1_date": null,
      "impact_t1_open_price": null,
      "impact_t1_close_price": null,
      "impact_t1_return": null,
      "impact_t1_relative_market_return": null,
      "impact_t1_status": "尚未收盤",
      "impact_t2_date": null,
      "impact_t2_open_price": null,
      "impact_t2_close_price": null,
      "impact_t2_return": null,
      "impact_t2_relative_market_return": null,
      "impact_t2_status": "尚未收盤",
      "impact_t3_date": null,
      "impact_t3_open_price": null,
      "impact_t3_close_price": null,
      "impact_t3_return": null,
      "impact_t3_relative_market_return": null,
      "impact_t3_status": "尚未收盤",
      "best_3d_return": null,
      "worst_3d_return": null,
      "relative_best_3d_return": null,
      "trade_best_3d_return": null,
      "trade_worst_3d_return": null,
      "trade_relative_best_3d_return": null,
      "trade_validation_status": "待回填",
      "trade_is_correct": null,
      "validation_status": "觀察中",
      "validation_window_status": "未滿3個交易日"
    },
    {
      "run_id": "20260615_001237_scheduled_3c68f2",
      "target_tw_date": "2026-06-15T00:00:00",
      "tw_ticker": "2308.TW",
      "tw_name": "台達電",
      "expected_direction": "看漲",
      "confidence_score": 36.2126343360926,
      "bullish_score": 36.2126343360926,
      "bearish_score": 0.0,
      "signal_count": 3,
      "bullish_signal_count": 3,
      "bearish_signal_count": 0,
      "best_win_rate": 0.652,
      "average_historical_return": 0.010916554349077902,
      "best_validation_win_rate": 0.6851851851851852,
      "main_us_sources": "SOXX",
      "main_reason": "SOXX 單日漲跌幅偏高",
      "min_lag_day": 2,
      "max_lag_day": 3,
      "created_at": "2026-06-15T00:13:56.649830",
      "beginner_decision": "看漲",
      "is_actionable": true,
      "market_risk_level": "正常",
      "risk_warning": "",
      "risk_adjusted_score": 36.2126343360926,
      "actual_return": null,
      "actual_direction": null,
      "is_correct": null,
      "open_price": null,
      "close_price": null,
      "previous_close_price": 2215.0,
      "validated_at": "2026-06-15T00:14:00.617146",
      "entry_price": null,
      "entry_price_date": null,
      "impact_entry_price": 2215.0,
      "impact_entry_price_date": "2026-06-12T00:00:00",
      "impact_actual_return": null,
      "impact_actual_direction": null,
      "impact_is_correct": null,
      "impact_validation_status": "觀察中",
      "t1_date": null,
      "t1_open_price": null,
      "t1_close_price": null,
      "t1_return": null,
      "t1_relative_market_return": null,
      "t1_status": "缺少目標日開盤價",
      "t2_date": null,
      "t2_open_price": null,
      "t2_close_price": null,
      "t2_return": null,
      "t2_relative_market_return": null,
      "t2_status": "缺少目標日開盤價",
      "t3_date": null,
      "t3_open_price": null,
      "t3_close_price": null,
      "t3_return": null,
      "t3_relative_market_return": null,
      "t3_status": "缺少目標日開盤價",
      "impact_t1_date": null,
      "impact_t1_open_price": null,
      "impact_t1_close_price": null,
      "impact_t1_return": null,
      "impact_t1_relative_market_return": null,
      "impact_t1_status": "尚未收盤",
      "impact_t2_date": null,
      "impact_t2_open_price": null,
      "impact_t2_close_price": null,
      "impact_t2_return": null,
      "impact_t2_relative_market_return": null,
      "impact_t2_status": "尚未收盤",
      "impact_t3_date": null,
      "impact_t3_open_price": null,
      "impact_t3_close_price": null,
      "impact_t3_return": null,
      "impact_t3_relative_market_return": null,
      "impact_t3_status": "尚未收盤",
      "best_3d_return": null,
      "worst_3d_return": null,
      "relative_best_3d_return": null,
      "trade_best_3d_return": null,
      "trade_worst_3d_return": null,
      "trade_relative_best_3d_return": null,
      "trade_validation_status": "待回填",
      "trade_is_correct": null,
      "validation_status": "觀察中",
      "validation_window_status": "未滿3個交易日"
    },
    {
      "run_id": "20260615_001237_scheduled_3c68f2",
      "target_tw_date": "2026-06-15T00:00:00",
      "tw_ticker": "2382.TW",
      "tw_name": "廣達",
      "expected_direction": "看漲",
      "confidence_score": 35.021104589251614,
      "bullish_score": 35.021104589251614,
      "bearish_score": 0.0,
      "signal_count": 1,
      "bullish_signal_count": 1,
      "bearish_signal_count": 0,
      "best_win_rate": 0.624,
      "average_historical_return": 0.011417426257106613,
      "best_validation_win_rate": 0.5714285714285714,
      "main_us_sources": "AMD",
      "main_reason": "AMD 單日漲跌幅偏高",
      "min_lag_day": 3,
      "max_lag_day": 3,
      "created_at": "2026-06-15T00:13:56.649830",
      "beginner_decision": "看漲",
      "is_actionable": true,
      "market_risk_level": "正常",
      "risk_warning": "",
      "risk_adjusted_score": 35.021104589251614,
      "actual_return": null,
      "actual_direction": null,
      "is_correct": null,
      "open_price": null,
      "close_price": null,
      "previous_close_price": 372.0,
      "validated_at": "2026-06-15T00:14:07.072272",
      "entry_price": null,
      "entry_price_date": null,
      "impact_entry_price": 372.0,
      "impact_entry_price_date": "2026-06-12T00:00:00",
      "impact_actual_return": null,
      "impact_actual_direction": null,
      "impact_is_correct": null,
      "impact_validation_status": "觀察中",
      "t1_date": null,
      "t1_open_price": null,
      "t1_close_price": null,
      "t1_return": null,
      "t1_relative_market_return": null,
      "t1_status": "缺少目標日開盤價",
      "t2_date": null,
      "t2_open_price": null,
      "t2_close_price": null,
      "t2_return": null,
      "t2_relative_market_return": null,
      "t2_status": "缺少目標日開盤價",
      "t3_date": null,
      "t3_open_price": null,
      "t3_close_price": null,
      "t3_return": null,
      "t3_relative_market_return": null,
      "t3_status": "缺少目標日開盤價",
      "impact_t1_date": null,
      "impact_t1_open_price": null,
      "impact_t1_close_price": null,
      "impact_t1_return": null,
      "impact_t1_relative_market_return": null,
      "impact_t1_status": "尚未收盤",
      "impact_t2_date": null,
      "impact_t2_open_price": null,
      "impact_t2_close_price": null,
      "impact_t2_return": null,
      "impact_t2_relative_market_return": null,
      "impact_t2_status": "尚未收盤",
      "impact_t3_date": null,
      "impact_t3_open_price": null,
      "impact_t3_close_price": null,
      "impact_t3_return": null,
      "impact_t3_relative_market_return": null,
      "impact_t3_status": "尚未收盤",
      "best_3d_return": null,
      "worst_3d_return": null,
      "relative_best_3d_return": null,
      "trade_best_3d_return": null,
      "trade_worst_3d_return": null,
      "trade_relative_best_3d_return": null,
      "trade_validation_status": "待回填",
      "trade_is_correct": null,
      "validation_status": "觀察中",
      "validation_window_status": "未滿3個交易日"
    },
    {
      "run_id": "20260615_001237_scheduled_3c68f2",
      "target_tw_date": "2026-06-15T00:00:00",
      "tw_ticker": "3231.TW",
      "tw_name": "緯創",
      "expected_direction": "看漲",
      "confidence_score": 34.53187537756789,
      "bullish_score": 34.53187537756789,
      "bearish_score": 0.0,
      "signal_count": 1,
      "bullish_signal_count": 1,
      "bearish_signal_count": 0,
      "best_win_rate": 0.616,
      "average_historical_return": 0.013298186090422057,
      "best_validation_win_rate": 0.5081967213114754,
      "main_us_sources": "AMD",
      "main_reason": "AMD 近 5 日漲跌幅偏高",
      "min_lag_day": 3,
      "max_lag_day": 3,
      "created_at": "2026-06-15T00:13:56.649830",
      "beginner_decision": "看漲",
      "is_actionable": true,
      "market_risk_level": "正常",
      "risk_warning": "",
      "risk_adjusted_score": 34.53187537756789,
      "actual_return": null,
      "actual_direction": null,
      "is_correct": null,
      "open_price": null,
      "close_price": null,
      "previous_close_price": 156.0,
      "validated_at": "2026-06-15T00:14:13.842072",
      "entry_price": null,
      "entry_price_date": null,
      "impact_entry_price": 156.0,
      "impact_entry_price_date": "2026-06-12T00:00:00",
      "impact_actual_return": null,
      "impact_actual_direction": null,
      "impact_is_correct": null,
      "impact_validation_status": "觀察中",
      "t1_date": null,
      "t1_open_price": null,
      "t1_close_price": null,
      "t1_return": null,
      "t1_relative_market_return": null,
      "t1_status": "缺少目標日開盤價",
      "t2_date": null,
      "t2_open_price": null,
      "t2_close_price": null,
      "t2_return": null,
      "t2_relative_market_return": null,
      "t2_status": "缺少目標日開盤價",
      "t3_date": null,
      "t3_open_price": null,
      "t3_close_price": null,
      "t3_return": null,
      "t3_relative_market_return": null,
      "t3_status": "缺少目標日開盤價",
      "impact_t1_date": null,
      "impact_t1_open_price": null,
      "impact_t1_close_price": null,
      "impact_t1_return": null,
      "impact_t1_relative_market_return": null,
      "impact_t1_status": "尚未收盤",
      "impact_t2_date": null,
      "impact_t2_open_price": null,
      "impact_t2_close_price": null,
      "impact_t2_return": null,
      "impact_t2_relative_market_return": null,
      "impact_t2_status": "尚未收盤",
      "impact_t3_date": null,
      "impact_t3_open_price": null,
      "impact_t3_close_price": null,
      "impact_t3_return": null,
      "impact_t3_relative_market_return": null,
      "impact_t3_status": "尚未收盤",
      "best_3d_return": null,
      "worst_3d_return": null,
      "relative_best_3d_return": null,
      "trade_best_3d_return": null,
      "trade_worst_3d_return": null,
      "trade_relative_best_3d_return": null,
      "trade_validation_status": "待回填",
      "trade_is_correct": null,
      "validation_status": "觀察中",
      "validation_window_status": "未滿3個交易日"
    },
    {
      "run_id": "20260615_001237_scheduled_3c68f2",
      "target_tw_date": "2026-06-15T00:00:00",
      "tw_ticker": "2317.TW",
      "tw_name": "鴻海",
      "expected_direction": "看漲",
      "confidence_score": 33.187326022456624,
      "bullish_score": 33.187326022456624,
      "bearish_score": 0.0,
      "signal_count": 1,
      "bullish_signal_count": 1,
      "bearish_signal_count": 0,
      "best_win_rate": 0.612,
      "average_historical_return": 0.011987032668941222,
      "best_validation_win_rate": 0.6122448979591837,
      "main_us_sources": "SMH",
      "main_reason": "SMH 單日漲跌幅偏高",
      "min_lag_day": 3,
      "max_lag_day": 3,
      "created_at": "2026-06-15T00:13:56.649830",
      "beginner_decision": "看漲",
      "is_actionable": true,
      "market_risk_level": "正常",
      "risk_warning": "",
      "risk_adjusted_score": 33.187326022456624,
      "actual_return": null,
      "actual_direction": null,
      "is_correct": null,
      "open_price": null,
      "close_price": null,
      "previous_close_price": 260.5,
      "validated_at": "2026-06-15T00:14:01.889963",
      "entry_price": null,
      "entry_price_date": null,
      "impact_entry_price": 260.5,
      "impact_entry_price_date": "2026-06-12T00:00:00",
      "impact_actual_return": null,
      "impact_actual_direction": null,
      "impact_is_correct": null,
      "impact_validation_status": "觀察中",
      "t1_date": null,
      "t1_open_price": null,
      "t1_close_price": null,
      "t1_return": null,
      "t1_relative_market_return": null,
      "t1_status": "缺少目標日開盤價",
      "t2_date": null,
      "t2_open_price": null,
      "t2_close_price": null,
      "t2_return": null,
      "t2_relative_market_return": null,
      "t2_status": "缺少目標日開盤價",
      "t3_date": null,
      "t3_open_price": null,
      "t3_close_price": null,
      "t3_return": null,
      "t3_relative_market_return": null,
      "t3_status": "缺少目標日開盤價",
      "impact_t1_date": null,
      "impact_t1_open_price": null,
      "impact_t1_close_price": null,
      "impact_t1_return": null,
      "impact_t1_relative_market_return": null,
      "impact_t1_status": "尚未收盤",
      "impact_t2_date": null,
      "impact_t2_open_price": null,
      "impact_t2_close_price": null,
      "impact_t2_return": null,
      "impact_t2_relative_market_return": null,
      "impact_t2_status": "尚未收盤",
      "impact_t3_date": null,
      "impact_t3_open_price": null,
      "impact_t3_close_price": null,
      "impact_t3_return": null,
      "impact_t3_relative_market_return": null,
      "impact_t3_status": "尚未收盤",
      "best_3d_return": null,
      "worst_3d_return": null,
      "relative_best_3d_return": null,
      "trade_best_3d_return": null,
      "trade_worst_3d_return": null,
      "trade_relative_best_3d_return": null,
      "trade_validation_status": "待回填",
      "trade_is_correct": null,
      "validation_status": "觀察中",
      "validation_window_status": "未滿3個交易日"
    },
    {
      "run_id": "20260615_001237_scheduled_3c68f2",
      "target_tw_date": "2026-06-15T00:00:00",
      "tw_ticker": "2891.TW",
      "tw_name": "中信金",
      "expected_direction": "看漲",
      "confidence_score": 32.531990987263256,
      "bullish_score": 32.531990987263256,
      "bearish_score": 0.0,
      "signal_count": 1,
      "bullish_signal_count": 1,
      "bearish_signal_count": 0,
      "best_win_rate": 0.636,
      "average_historical_return": 0.009148445097125483,
      "best_validation_win_rate": 0.6282051282051282,
      "main_us_sources": "XLF",
      "main_reason": "XLF 單日漲跌幅偏高",
      "min_lag_day": 3,
      "max_lag_day": 3,
      "created_at": "2026-06-15T00:13:56.649830",
      "beginner_decision": "看漲",
      "is_actionable": true,
      "market_risk_level": "正常",
      "risk_warning": "",
      "risk_adjusted_score": 32.531990987263256,
      "actual_return": null,
      "actual_direction": null,
      "is_correct": null,
      "open_price": null,
      "close_price": null,
      "previous_close_price": 67.6,
      "validated_at": "2026-06-15T00:14:10.341316",
      "entry_price": null,
      "entry_price_date": null,
      "impact_entry_price": 67.6,
      "impact_entry_price_date": "2026-06-12T00:00:00",
      "impact_actual_return": null,
      "impact_actual_direction": null,
      "impact_is_correct": null,
      "impact_validation_status": "觀察中",
      "t1_date": null,
      "t1_open_price": null,
      "t1_close_price": null,
      "t1_return": null,
      "t1_relative_market_return": null,
      "t1_status": "缺少目標日開盤價",
      "t2_date": null,
      "t2_open_price": null,
      "t2_close_price": null,
      "t2_return": null,
      "t2_relative_market_return": null,
      "t2_status": "缺少目標日開盤價",
      "t3_date": null,
      "t3_open_price": null,
      "t3_close_price": null,
      "t3_return": null,
      "t3_relative_market_return": null,
      "t3_status": "缺少目標日開盤價",
      "impact_t1_date": null,
      "impact_t1_open_price": null,
      "impact_t1_close_price": null,
      "impact_t1_return": null,
      "impact_t1_relative_market_return": null,
      "impact_t1_status": "尚未收盤",
      "impact_t2_date": null,
      "impact_t2_open_price": null,
      "impact_t2_close_price": null,
      "impact_t2_return": null,
      "impact_t2_relative_market_return": null,
      "impact_t2_status": "尚未收盤",
      "impact_t3_date": null,
      "impact_t3_open_price": null,
      "impact_t3_close_price": null,
      "impact_t3_return": null,
      "impact_t3_relative_market_return": null,
      "impact_t3_status": "尚未收盤",
      "best_3d_return": null,
      "worst_3d_return": null,
      "relative_best_3d_return": null,
      "trade_best_3d_return": null,
      "trade_worst_3d_return": null,
      "trade_relative_best_3d_return": null,
      "trade_validation_status": "待回填",
      "trade_is_correct": null,
      "validation_status": "觀察中",
      "validation_window_status": "未滿3個交易日"
    },
    {
      "run_id": "20260615_001237_scheduled_3c68f2",
      "target_tw_date": "2026-06-15T00:00:00",
      "tw_ticker": "2379.TW",
      "tw_name": "瑞昱",
      "expected_direction": "多空混合",
      "confidence_score": 1.7502803867639969,
      "bullish_score": 43.8064679195058,
      "bearish_score": 45.556748306269796,
      "signal_count": 4,
      "bullish_signal_count": 2,
      "bearish_signal_count": 2,
      "best_win_rate": 0.6867469879518072,
      "average_historical_return": -0.014782529821314627,
      "best_validation_win_rate": 0.6020408163265306,
      "main_us_sources": "META",
      "main_reason": "META 接近 20 日低點觸發",
      "min_lag_day": 2,
      "max_lag_day": 3,
      "created_at": "2026-06-15T00:13:56.649830",
      "beginner_decision": "多空混合",
      "is_actionable": false,
      "market_risk_level": "正常",
      "risk_warning": "多空訊號衝突，方向優勢不足",
      "risk_adjusted_score": 1.7502803867639969,
      "actual_return": null,
      "actual_direction": null,
      "is_correct": null,
      "open_price": null,
      "close_price": null,
      "previous_close_price": 618.0,
      "validated_at": "2026-06-15T00:14:05.624347",
      "entry_price": null,
      "entry_price_date": null,
      "impact_entry_price": 618.0,
      "impact_entry_price_date": "2026-06-12T00:00:00",
      "impact_actual_return": null,
      "impact_actual_direction": null,
      "impact_is_correct": null,
      "impact_validation_status": "不列入命中率",
      "t1_date": null,
      "t1_open_price": null,
      "t1_close_price": null,
      "t1_return": null,
      "t1_relative_market_return": null,
      "t1_status": "缺少目標日開盤價",
      "t2_date": null,
      "t2_open_price": null,
      "t2_close_price": null,
      "t2_return": null,
      "t2_relative_market_return": null,
      "t2_status": "缺少目標日開盤價",
      "t3_date": null,
      "t3_open_price": null,
      "t3_close_price": null,
      "t3_return": null,
      "t3_relative_market_return": null,
      "t3_status": "缺少目標日開盤價",
      "impact_t1_date": null,
      "impact_t1_open_price": null,
      "impact_t1_close_price": null,
      "impact_t1_return": null,
      "impact_t1_relative_market_return": null,
      "impact_t1_status": "尚未收盤",
      "impact_t2_date": null,
      "impact_t2_open_price": null,
      "impact_t2_close_price": null,
      "impact_t2_return": null,
      "impact_t2_relative_market_return": null,
      "impact_t2_status": "尚未收盤",
      "impact_t3_date": null,
      "impact_t3_open_price": null,
      "impact_t3_close_price": null,
      "impact_t3_return": null,
      "impact_t3_relative_market_return": null,
      "impact_t3_status": "尚未收盤",
      "best_3d_return": null,
      "worst_3d_return": null,
      "relative_best_3d_return": null,
      "trade_best_3d_return": null,
      "trade_worst_3d_return": null,
      "trade_relative_best_3d_return": null,
      "trade_validation_status": "不列入命中率",
      "trade_is_correct": null,
      "validation_status": "不列入命中率",
      "validation_window_status": "未滿3個交易日"
    }
  ],
  "signals": [
    {
      "run_id": "20260615_001237_scheduled_3c68f2",
      "target_tw_date": "2026-06-15T00:00:00",
      "tw_ticker": "2330.TW",
      "us_ticker": "SMH",
      "signal_side": "bullish",
      "trigger_text": "SMH 單日漲跌幅偏高",
      "lag_day": 1,
      "signal_score": 56.92529654291783,
      "historical_win_rate": 0.812,
      "historical_average_return": 0.01490420560647845,
      "validation_win_rate": 0.6632653061224489,
      "sample_count": 250,
      "created_at": "2026-06-15T00:13:56.649830"
    },
    {
      "run_id": "20260615_001237_scheduled_3c68f2",
      "target_tw_date": "2026-06-15T00:00:00",
      "tw_ticker": "2454.TW",
      "us_ticker": "SMH",
      "signal_side": "bullish",
      "trigger_text": "SMH 單日漲跌幅偏高",
      "lag_day": 2,
      "signal_score": 54.9234114967349,
      "historical_win_rate": 0.736,
      "historical_average_return": 0.016640558825290176,
      "validation_win_rate": 0.6020408163265306,
      "sample_count": 250,
      "created_at": "2026-06-15T00:13:56.649830"
    },
    {
      "run_id": "20260615_001237_scheduled_3c68f2",
      "target_tw_date": "2026-06-15T00:00:00",
      "tw_ticker": "2454.TW",
      "us_ticker": "SMH",
      "signal_side": "bullish",
      "trigger_text": "SMH 單日漲跌幅偏高",
      "lag_day": 3,
      "signal_score": 53.02061981934224,
      "historical_win_rate": 0.708,
      "historical_average_return": 0.017645193877852187,
      "validation_win_rate": 0.6122448979591837,
      "sample_count": 250,
      "created_at": "2026-06-15T00:13:56.649830"
    },
    {
      "run_id": "20260615_001237_scheduled_3c68f2",
      "target_tw_date": "2026-06-15T00:00:00",
      "tw_ticker": "3711.TW",
      "us_ticker": "SMH",
      "signal_side": "bullish",
      "trigger_text": "SMH 單日漲跌幅偏高",
      "lag_day": 1,
      "signal_score": 52.49213179071572,
      "historical_win_rate": 0.756,
      "historical_average_return": 0.014858808832134694,
      "validation_win_rate": 0.6938775510204082,
      "sample_count": 250,
      "created_at": "2026-06-15T00:13:56.649830"
    },
    {
      "run_id": "20260615_001237_scheduled_3c68f2",
      "target_tw_date": "2026-06-15T00:00:00",
      "tw_ticker": "3711.TW",
      "us_ticker": "SOXX",
      "signal_side": "bullish",
      "trigger_text": "SOXX 單日漲跌幅偏高",
      "lag_day": 1,
      "signal_score": 52.130681599877455,
      "historical_win_rate": 0.756,
      "historical_average_return": 0.01481422043881081,
      "validation_win_rate": 0.6666666666666666,
      "sample_count": 250,
      "created_at": "2026-06-15T00:13:56.649830"
    },
    {
      "run_id": "20260615_001237_scheduled_3c68f2",
      "target_tw_date": "2026-06-15T00:00:00",
      "tw_ticker": "2330.TW",
      "us_ticker": "SOXX",
      "signal_side": "bullish",
      "trigger_text": "SOXX 單日漲跌幅偏高",
      "lag_day": 1,
      "signal_score": 51.924832611797044,
      "historical_win_rate": 0.776,
      "historical_average_return": 0.013735537608020484,
      "validation_win_rate": 0.6388888888888888,
      "sample_count": 250,
      "created_at": "2026-06-15T00:13:56.649830"
    },
    {
      "run_id": "20260615_001237_scheduled_3c68f2",
      "target_tw_date": "2026-06-15T00:00:00",
      "tw_ticker": "3711.TW",
      "us_ticker": "SMH",
      "signal_side": "bullish",
      "trigger_text": "SMH 單日漲跌幅偏高",
      "lag_day": 3,
      "signal_score": 50.203699151558396,
      "historical_win_rate": 0.676,
      "historical_average_return": 0.018160452751360082,
      "validation_win_rate": 0.6530612244897959,
      "sample_count": 250,
      "created_at": "2026-06-15T00:13:56.649830"
    },
    {
      "run_id": "20260615_001237_scheduled_3c68f2",
      "target_tw_date": "2026-06-15T00:00:00",
      "tw_ticker": "2379.TW",
      "us_ticker": "META",
      "signal_side": "bearish",
      "trigger_text": "META 接近 20 日低點觸發",
      "lag_day": 2,
      "signal_score": 45.556748306269796,
      "historical_win_rate": 0.6867469879518072,
      "historical_average_return": -0.014782529821314627,
      "validation_win_rate": 0.54,
      "sample_count": 83,
      "created_at": "2026-06-15T00:13:56.649830"
    },
    {
      "run_id": "20260615_001237_scheduled_3c68f2",
      "target_tw_date": "2026-06-15T00:00:00",
      "tw_ticker": "2379.TW",
      "us_ticker": "SMH",
      "signal_side": "bullish",
      "trigger_text": "SMH 單日漲跌幅偏高",
      "lag_day": 2,
      "signal_score": 43.8064679195058,
      "historical_win_rate": 0.684,
      "historical_average_return": 0.013214246951304997,
      "validation_win_rate": 0.6020408163265306,
      "sample_count": 250,
      "created_at": "2026-06-15T00:13:56.649830"
    },
    {
      "run_id": "20260615_001237_scheduled_3c68f2",
      "target_tw_date": "2026-06-15T00:00:00",
      "tw_ticker": "2379.TW",
      "us_ticker": "SMH",
      "signal_side": "bullish",
      "trigger_text": "SMH 單日漲跌幅偏高",
      "lag_day": 3,
      "signal_score": 43.40846787312746,
      "historical_win_rate": 0.668,
      "historical_average_return": 0.014071128862899077,
      "validation_win_rate": 0.5612244897959183,
      "sample_count": 250,
      "created_at": "2026-06-15T00:13:56.649830"
    },
    {
      "run_id": "20260615_001237_scheduled_3c68f2",
      "target_tw_date": "2026-06-15T00:00:00",
      "tw_ticker": "3034.TW",
      "us_ticker": "SMH",
      "signal_side": "bullish",
      "trigger_text": "SMH 近 3 日漲跌幅偏高",
      "lag_day": 3,
      "signal_score": 43.19788766612803,
      "historical_win_rate": 0.672,
      "historical_average_return": 0.015096047623568667,
      "validation_win_rate": 0.5742574257425742,
      "sample_count": 250,
      "created_at": "2026-06-15T00:13:56.649830"
    },
    {
      "run_id": "20260615_001237_scheduled_3c68f2",
      "target_tw_date": "2026-06-15T00:00:00",
      "tw_ticker": "3034.TW",
      "us_ticker": "SOXX",
      "signal_side": "bullish",
      "trigger_text": "SOXX 單日漲跌幅偏高",
      "lag_day": 3,
      "signal_score": 42.60633135830018,
      "historical_win_rate": 0.652,
      "historical_average_return": 0.015261889779414098,
      "validation_win_rate": 0.5648148148148148,
      "sample_count": 250,
      "created_at": "2026-06-15T00:13:56.649830"
    },
    {
      "run_id": "20260615_001237_scheduled_3c68f2",
      "target_tw_date": "2026-06-15T00:00:00",
      "tw_ticker": "3034.TW",
      "us_ticker": "SOXX",
      "signal_side": "bullish",
      "trigger_text": "SOXX 近 3 日漲跌幅偏高",
      "lag_day": 3,
      "signal_score": 42.5886383130734,
      "historical_win_rate": 0.668,
      "historical_average_return": 0.014254518205595314,
      "validation_win_rate": 0.5826086956521739,
      "sample_count": 250,
      "created_at": "2026-06-15T00:13:56.649830"
    },
    {
      "run_id": "20260615_001237_scheduled_3c68f2",
      "target_tw_date": "2026-06-15T00:00:00",
      "tw_ticker": "2303.TW",
      "us_ticker": "SOXX",
      "signal_side": "bullish",
      "trigger_text": "SOXX 單日漲跌幅偏高",
      "lag_day": 2,
      "signal_score": 42.389086346393384,
      "historical_win_rate": 0.668,
      "historical_average_return": 0.012918896345627168,
      "validation_win_rate": 0.5833333333333334,
      "sample_count": 250,
      "created_at": "2026-06-15T00:13:56.649830"
    },
    {
      "run_id": "20260615_001237_scheduled_3c68f2",
      "target_tw_date": "2026-06-15T00:00:00",
      "tw_ticker": "2379.TW",
      "us_ticker": "META",
      "signal_side": "bearish",
      "trigger_text": "META 接近 20 日低點觸發",
      "lag_day": 3,
      "signal_score": 40.887537837266265,
      "historical_win_rate": 0.6385542168674698,
      "historical_average_return": -0.014168769063202897,
      "validation_win_rate": 0.54,
      "sample_count": 83,
      "created_at": "2026-06-15T00:13:56.649830"
    },
    {
      "run_id": "20260615_001237_scheduled_3c68f2",
      "target_tw_date": "2026-06-15T00:00:00",
      "tw_ticker": "2881.TW",
      "us_ticker": "XLF",
      "signal_side": "bullish",
      "trigger_text": "XLF 單日漲跌幅偏高",
      "lag_day": 3,
      "signal_score": 40.5534454998,
      "historical_win_rate": 0.688,
      "historical_average_return": 0.012048858977458466,
      "validation_win_rate": 0.5512820512820513,
      "sample_count": 250,
      "created_at": "2026-06-15T00:13:56.649830"
    },
    {
      "run_id": "20260615_001237_scheduled_3c68f2",
      "target_tw_date": "2026-06-15T00:00:00",
      "tw_ticker": "2881.TW",
      "us_ticker": "XLF",
      "signal_side": "bullish",
      "trigger_text": "XLF 單日漲跌幅偏高",
      "lag_day": 1,
      "signal_score": 37.53116581961722,
      "historical_win_rate": 0.712,
      "historical_average_return": 0.008079711852721565,
      "validation_win_rate": 0.6410256410256411,
      "sample_count": 250,
      "created_at": "2026-06-15T00:13:56.649830"
    },
    {
      "run_id": "20260615_001237_scheduled_3c68f2",
      "target_tw_date": "2026-06-15T00:00:00",
      "tw_ticker": "2881.TW",
      "us_ticker": "SMH",
      "signal_side": "bullish",
      "trigger_text": "SMH 單日漲跌幅偏高",
      "lag_day": 3,
      "signal_score": 36.93519851257921,
      "historical_win_rate": 0.684,
      "historical_average_return": 0.009038809638607153,
      "validation_win_rate": 0.5714285714285714,
      "sample_count": 250,
      "created_at": "2026-06-15T00:13:56.649830"
    },
    {
      "run_id": "20260615_001237_scheduled_3c68f2",
      "target_tw_date": "2026-06-15T00:00:00",
      "tw_ticker": "2308.TW",
      "us_ticker": "SOXX",
      "signal_side": "bullish",
      "trigger_text": "SOXX 單日漲跌幅偏高",
      "lag_day": 2,
      "signal_score": 36.2126343360926,
      "historical_win_rate": 0.652,
      "historical_average_return": 0.010916554349077902,
      "validation_win_rate": 0.6851851851851852,
      "sample_count": 250,
      "created_at": "2026-06-15T00:13:56.649830"
    },
    {
      "run_id": "20260615_001237_scheduled_3c68f2",
      "target_tw_date": "2026-06-15T00:00:00",
      "tw_ticker": "2308.TW",
      "us_ticker": "SMH",
      "signal_side": "bullish",
      "trigger_text": "SMH 單日漲跌幅偏高",
      "lag_day": 2,
      "signal_score": 35.52615793966375,
      "historical_win_rate": 0.644,
      "historical_average_return": 0.010881425126456906,
      "validation_win_rate": 0.6836734693877551,
      "sample_count": 250,
      "created_at": "2026-06-15T00:13:56.649830"
    },
    {
      "run_id": "20260615_001237_scheduled_3c68f2",
      "target_tw_date": "2026-06-15T00:00:00",
      "tw_ticker": "2382.TW",
      "us_ticker": "AMD",
      "signal_side": "bullish",
      "trigger_text": "AMD 單日漲跌幅偏高",
      "lag_day": 3,
      "signal_score": 35.021104589251614,
      "historical_win_rate": 0.624,
      "historical_average_return": 0.011417426257106613,
      "validation_win_rate": 0.5714285714285714,
      "sample_count": 250,
      "created_at": "2026-06-15T00:13:56.649830"
    },
    {
      "run_id": "20260615_001237_scheduled_3c68f2",
      "target_tw_date": "2026-06-15T00:00:00",
      "tw_ticker": "3231.TW",
      "us_ticker": "AMD",
      "signal_side": "bullish",
      "trigger_text": "AMD 近 5 日漲跌幅偏高",
      "lag_day": 3,
      "signal_score": 34.53187537756789,
      "historical_win_rate": 0.616,
      "historical_average_return": 0.013298186090422057,
      "validation_win_rate": 0.5081967213114754,
      "sample_count": 250,
      "created_at": "2026-06-15T00:13:56.649830"
    },
    {
      "run_id": "20260615_001237_scheduled_3c68f2",
      "target_tw_date": "2026-06-15T00:00:00",
      "tw_ticker": "2308.TW",
      "us_ticker": "SMH",
      "signal_side": "bullish",
      "trigger_text": "SMH 單日漲跌幅偏高",
      "lag_day": 3,
      "signal_score": 34.26547153963913,
      "historical_win_rate": 0.62,
      "historical_average_return": 0.012268175566453996,
      "validation_win_rate": 0.6632653061224489,
      "sample_count": 250,
      "created_at": "2026-06-15T00:13:56.649830"
    },
    {
      "run_id": "20260615_001237_scheduled_3c68f2",
      "target_tw_date": "2026-06-15T00:00:00",
      "tw_ticker": "2317.TW",
      "us_ticker": "SMH",
      "signal_side": "bullish",
      "trigger_text": "SMH 單日漲跌幅偏高",
      "lag_day": 3,
      "signal_score": 33.187326022456624,
      "historical_win_rate": 0.612,
      "historical_average_return": 0.011987032668941222,
      "validation_win_rate": 0.6122448979591837,
      "sample_count": 250,
      "created_at": "2026-06-15T00:13:56.649830"
    },
    {
      "run_id": "20260615_001237_scheduled_3c68f2",
      "target_tw_date": "2026-06-15T00:00:00",
      "tw_ticker": "2891.TW",
      "us_ticker": "XLF",
      "signal_side": "bullish",
      "trigger_text": "XLF 單日漲跌幅偏高",
      "lag_day": 3,
      "signal_score": 32.531990987263256,
      "historical_win_rate": 0.636,
      "historical_average_return": 0.009148445097125483,
      "validation_win_rate": 0.6282051282051282,
      "sample_count": 250,
      "created_at": "2026-06-15T00:13:56.649830"
    }
  ]
}